params_storage/__init__.py
params_storage/params_storage.py
params_storage-0.8.dist-info/LICENSE
params_storage-0.8.dist-info/METADATA
params_storage-0.8.dist-info/WHEEL
params_storage-0.8.dist-info/top_level.txt
params_storage-0.8.dist-info/RECORD
