Metadata-Version: 2.1
Name: params-storage
Version: 0.8
Summary: Key-value storage to store hyperparameters for machine learning models.
Home-page: https://github.com/darkhan-ai/params-storage
License: MIT
License-File: LICENSE
